Hack4u/__init__.py
Hack4u/courses.py
Hack4u/utils.py
hack4u_auris-0.1.0.dist-info/METADATA
hack4u_auris-0.1.0.dist-info/WHEEL
hack4u_auris-0.1.0.dist-info/top_level.txt
hack4u_auris-0.1.0.dist-info/RECORD
