Metadata-Version: 2.4
Name: Hack4u_auris
Version: 0.1.0
Summary: Biblioteca para consultar cursos de Hack4u.
Home-page: https://hack4u.io
Author: Aurisssss
Dynamic: author
Dynamic: description
Dynamic: description-content-type
Dynamic: home-page
Dynamic: summary
